nonebot_plugin_shiro_web_console/__init__.py
nonebot_plugin_shiro_web_console/config.py
nonebot_plugin_shiro_web_console/static/index.html
nonebot_plugin_shiro_web_console-0.1.14.dist-info/METADATA
nonebot_plugin_shiro_web_console-0.1.14.dist-info/WHEEL
nonebot_plugin_shiro_web_console-0.1.14.dist-info/licenses/LICENSE
nonebot_plugin_shiro_web_console-0.1.14.dist-info/RECORD
