Metadata-Version: 2.4
Name: nonebot-plugin-shiro-web-console
Version: 0.1.14
Summary: 一个用于 NoneBot2 的网页控制台插件，支持通过浏览器查看日志和发送消息
Project-URL: Homepage, https://github.com/luojisama/nonebot-plugin-shiro-web-console
Project-URL: Bug Tracker, https://github.com/luojisama/nonebot-plugin-shiro-web-console/issues
Project-URL: Repository, https://github.com/luojisama/nonebot-plugin-shiro-web-console
Author-email: luojisama <2534316454@qq.com>
License: MIT
License-File: LICENSE
Keywords: console,nonebot,nonebot2,plugin,webconsole
Classifier: Development Status :: 4 - Beta
Classifier: Intended Audience :: Developers
Classifier: License :: OSI Approved :: MIT License
Classifier: Operating System :: OS Independent
Classifier: Programming Language :: Python :: 3
Classifier: Programming Language :: Python :: 3.9
Classifier: Programming Language :: Python :: 3.10
Classifier: Programming Language :: Python :: 3.11
Classifier: Programming Language :: Python :: 3.12
Classifier: Topic :: Communications :: Chat
Requires-Python: >=3.9
Requires-Dist: fastapi>=0.95.0
Requires-Dist: httpx>=0.23.0
Requires-Dist: jinja2>=3.1.0
Requires-Dist: nonebot-adapter-onebot>=2.4.0
Requires-Dist: nonebot-plugin-localstore>=0.6.0
Requires-Dist: nonebot2>=2.2.0
Requires-Dist: pydantic
